pyEdgeEval-0.2.8.dist-info/top_level.txt
pyEdgeEval-0.2.8.dist-info/METADATA
pyEdgeEval-0.2.8.dist-info/RECORD
pyEdgeEval-0.2.8.dist-info/LICENSES.md
pyEdgeEval-0.2.8.dist-info/WHEEL
pyEdgeEval-0.2.8.dist-info/LICENSE
pyEdgeEval/info.py
pyEdgeEval/__init__.py
pyEdgeEval/helpers/convert_cityscapes.py
pyEdgeEval/helpers/evaluate_bsds500.py
pyEdgeEval/helpers/evaluate_cityscapes.py
pyEdgeEval/helpers/__init__.py
pyEdgeEval/helpers/evaluate_sbd.py
pyEdgeEval/helpers/convert_sbd.py
pyEdgeEval/common/utils.py
pyEdgeEval/common/metrics.py
pyEdgeEval/common/__init__.py
pyEdgeEval/common/multi_label/calculate_metrics.py
pyEdgeEval/common/multi_label/io.py
pyEdgeEval/common/multi_label/utils.py
pyEdgeEval/common/multi_label/options.py
pyEdgeEval/common/multi_label/edge_decoding.py
pyEdgeEval/common/multi_label/evaluate_boundaries.py
pyEdgeEval/common/multi_label/__init__.py
pyEdgeEval/common/multi_label/edge_encoding.py
pyEdgeEval/common/binary_label/calculate_metrics.py
pyEdgeEval/common/binary_label/io.py
pyEdgeEval/common/binary_label/evaluate_boundaries.py
pyEdgeEval/common/binary_label/__init__.py
pyEdgeEval/common/binary_label/visualize.py
pyEdgeEval/edge_tools/mask2edge_loop.py
pyEdgeEval/edge_tools/__init__.py
pyEdgeEval/edge_tools/transforms.py
pyEdgeEval/edge_tools/mask2edge_mp.py
pyEdgeEval/preprocess/__init__.py
pyEdgeEval/preprocess/nms/fast_nms.py
pyEdgeEval/preprocess/nms/toolbox.py
pyEdgeEval/preprocess/nms/__init__.py
pyEdgeEval/preprocess/thin/bwmorph_thin.py
pyEdgeEval/preprocess/thin/thin.py
pyEdgeEval/preprocess/thin/__init__.py
pyEdgeEval/utils/timer.py
pyEdgeEval/utils/progressbar.py
pyEdgeEval/utils/path.py
pyEdgeEval/utils/distance_transforms.py
pyEdgeEval/utils/__init__.py
pyEdgeEval/utils/logger.py
pyEdgeEval/utils/mat_utils.py
pyEdgeEval/utils/convert_formats.py
pyEdgeEval/visualization/pr_curve.py
pyEdgeEval/visualization/__init__.py
pyEdgeEval/evaluators/binary_evaluator.py
pyEdgeEval/evaluators/cityscapes.py
pyEdgeEval/evaluators/multilabel_evaluator.py
pyEdgeEval/evaluators/__init__.py
pyEdgeEval/evaluators/bsds.py
pyEdgeEval/evaluators/half_cityscapes.py
pyEdgeEval/evaluators/base.py
