Metadata-Version: 2.1
Name: pyEdgeEval
Version: 0.2.8
Summary: Python Edge Evaluation Tools
Home-page: https://github.com/haruishi43/py-edge-eval
Author: haruishi43
Author-email: haruyaishikawa@keio.jp
License: MIT
Keywords: Edge Detection,Semantic Boundary Detection,Computer Vision
Classifier: Development Status :: 3 - Alpha
Classifier: Intended Audience :: Developers
Classifier: Natural Language :: English
Classifier: Programming Language :: Python
Classifier: Programming Language :: Python :: 3.7
Classifier: Programming Language :: Python :: 3.8
Classifier: Programming Language :: Python :: 3.9
Classifier: Programming Language :: Python :: 3.10
Requires-Python: >=3.7
License-File: LICENSE
License-File: LICENSES.md
Requires-Dist: numpy
Requires-Dist: Cython
